funcarray/__init__.py
funcarray/func_array.py
FuncArray-0.0.1.dist-info/LICENSE.txt
FuncArray-0.0.1.dist-info/METADATA
FuncArray-0.0.1.dist-info/WHEEL
FuncArray-0.0.1.dist-info/top_level.txt
FuncArray-0.0.1.dist-info/RECORD
