Metadata-Version: 2.1
Name: FuncArray
Version: 0.0.1
Summary: A functional array class with elements computed on demand.
Home-page: https://github.com/LeonardoIalongo/FuncArray
Author: Leonardo Niccolò Ialongo
Author-email: leonardo.ialongo@gmail.com
License: GNU General Public License v3
Platform: UNKNOWN
Classifier: Development Status :: 2 - Pre-Alpha
Classifier: License :: OSI Approved :: GNU General Public License v3 (GPLv3)
Classifier: Natural Language :: English
Classifier: Programming Language :: Python :: 3
Classifier: Programming Language :: Python :: 3.7
Classifier: Programming Language :: Python :: 3.8
Classifier: Programming Language :: Python :: 3.9
Classifier: Operating System :: OS Independent
Requires-Python: >=3.0
Requires-Dist: numpy (>=1.15)
Requires-Dist: numba (>=0.55)
